reactpy_utils/__init__.py
reactpy_utils/class_component.py
reactpy_utils/copy_to_clipboard.py
reactpy_utils/document_title.py
reactpy_utils/dynamic_context.py
reactpy_utils/local_storage.py
reactpy_utils/props.py
reactpy_utils/py.typed
reactpy_utils/script.py
reactpy_utils/static_counter.py
reactpy_utils/types.py
reactpy_utils/unique_sequence.py
reactpy_utils/use_query.py
reactpy_utils/when.py
reactpy_utils-0.0.33.dist-info/METADATA
reactpy_utils-0.0.33.dist-info/WHEEL
reactpy_utils-0.0.33.dist-info/licenses/LICENSE.md
reactpy_utils-0.0.33.dist-info/RECORD
