Metadata-Version: 2.4
Name: reactpy_utils
Version: 0.0.33
Summary: A collection of utilities for ReactPy.
Project-URL: Changelog, https://stevej2608.github.io/reactpy-utils/latest/about/changelog/
Project-URL: Documentation, https://github.com/stevej2608/reactpy-utils#readme
Project-URL: Source, https://github.com/stevej2608/reactpy-utils
Author-email: Steve Jones <jonesst2608@gmail.com>
License-Expression: MIT
License-File: LICENSE.md
Keywords: React,ReactJS,ReactPy,components
Classifier: Development Status :: 4 - Beta
Classifier: Environment :: Web Environment
Classifier: Intended Audience :: Developers
Classifier: Intended Audience :: Science/Research
Classifier: Operating System :: OS Independent
Classifier: Programming Language :: Python :: 3.9
Classifier: Programming Language :: Python :: 3.10
Classifier: Programming Language :: Python :: 3.11
Classifier: Programming Language :: Python :: 3.12
Classifier: Topic :: Multimedia :: Graphics
Classifier: Topic :: Software Development :: User Interfaces
Classifier: Topic :: Software Development :: Widget Sets
Classifier: Typing :: Typed
Requires-Python: >=3.9
Requires-Dist: pydantic
Requires-Dist: reactpy-router>=1.0.3
Requires-Dist: reactpy>=1.0.0
Requires-Dist: typing-extensions
